ScoringPy/__init__.py
ScoringPy/module.py
ScoringPy-1.1.6.dist-info/LICENSE
ScoringPy-1.1.6.dist-info/METADATA
ScoringPy-1.1.6.dist-info/WHEEL
ScoringPy-1.1.6.dist-info/top_level.txt
ScoringPy-1.1.6.dist-info/RECORD
