Metadata-Version: 2.1
Name: ScoringPy
Version: 1.1.6
Summary: ScoringPy is an open-source Python library designed to streamline the development and deployment of classical credit scorecards.
Home-page: https://github.com/Qubdi/ScoringPy
Author: Anri Tvalabeishvili, Kristine Dzneladze, Akaki Benidze
Author-email: QubdiSolutions@gmail.com
Project-URL: Documentation, https://scoringpy.readthedocs.io/en/latest
Project-URL: HomePage, https://github.com/Qubdi/ScoringPy
Project-URL: Tracker, https://github.com/Qubdi/ScoringPy/issues
Classifier: Programming Language :: Python :: 3
Classifier: License :: OSI Approved :: MIT License
Classifier: Operating System :: OS Independent
Requires-Python: >=3.6
License-File: LICENSE
Requires-Dist: numpy
Requires-Dist: pandas
Requires-Dist: scikit-learn
Requires-Dist: matplotlib
Requires-Dist: seaborn
